core_changelog_md/__init__.py
core_changelog_md/exceptions.py
core_changelog_md/common/__init__.py
core_changelog_md/common/enums.py
core_changelog_md/common/exceptions.py
core_changelog_md/objects/__init__.py
core_changelog_md/objects/changelog.py
core_changelog_md/objects/changes.py
core_changelog_md/objects/version.py
core_changelog_md-1.5.6.dist-info/METADATA
core_changelog_md-1.5.6.dist-info/WHEEL
core_changelog_md-1.5.6.dist-info/top_level.txt
core_changelog_md-1.5.6.dist-info/RECORD
