Metadata-Version: 2.1
Name: core-changelog-md
Version: 1.5.6
Summary: core-changelog-md for cli-changelog-md
Home-page: https://gitlab.com/kappasama.ks/openapi_django
Author: Y. Chudakov
Author-email: kappasama.ks@gmail.com
Classifier: Programming Language :: Python :: 3
Requires-Python: >=3.8
Requires-Dist: setuptools (>=57.0.0)
Requires-Dist: packaging (==21.3)
Requires-Dist: pytest (>=7.1.2)
Requires-Dist: sortedcontainers (>=2.4.0)
